{
  "scene": {
    "id": "typical_1v1",
    "language": " this [0]  player  over .  You  want  to  go [1]  over  here .",
    "step": 0.02,
    "objects": [
      {
        "id": "ball",
        "type": "Ball",
        "position": [],
        "velocity": []
      }
    ],
    "annotations": [
      {
        "id": "0",
        "type": "Point",
        "point": {
          "x": 8.414988,
          "y": 6.19239235
        }
      },
      {
        "id": "1",
        "type": "Point",
        "point": {
          "x": -6.33668852,
          "y": -0.7606283
        }
      }
    ],
    "tokens": {
      "5.279995": " this [0]",
      "5.719995": " player",
      "6.369995": " over",
      "7.26999474": ".",
      "9.200044": " You",
      "9.610044": " want",
      "9.930044": " to",
      "10.130044": " go [1]",
      "10.3500433": " over",
      "10.7300434": " here",
      "11.1900434": "."
    },
    "clickTimes": {
      "0": 5.139996,
      "1": 10.1800432
    }
  }
}